google/cloud/webrisk/__init__.py
google/cloud/webrisk/gapic_version.py
google/cloud/webrisk/py.typed
google/cloud/webrisk_v1/__init__.py
google/cloud/webrisk_v1/gapic_metadata.json
google/cloud/webrisk_v1/gapic_version.py
google/cloud/webrisk_v1/py.typed
google/cloud/webrisk_v1/services/__init__.py
google/cloud/webrisk_v1/services/web_risk_service/__init__.py
google/cloud/webrisk_v1/services/web_risk_service/async_client.py
google/cloud/webrisk_v1/services/web_risk_service/client.py
google/cloud/webrisk_v1/services/web_risk_service/transports/__init__.py
google/cloud/webrisk_v1/services/web_risk_service/transports/base.py
google/cloud/webrisk_v1/services/web_risk_service/transports/grpc.py
google/cloud/webrisk_v1/services/web_risk_service/transports/grpc_asyncio.py
google/cloud/webrisk_v1/services/web_risk_service/transports/rest.py
google/cloud/webrisk_v1/services/web_risk_service/transports/rest_base.py
google/cloud/webrisk_v1/types/__init__.py
google/cloud/webrisk_v1/types/webrisk.py
google/cloud/webrisk_v1beta1/__init__.py
google/cloud/webrisk_v1beta1/gapic_metadata.json
google/cloud/webrisk_v1beta1/gapic_version.py
google/cloud/webrisk_v1beta1/py.typed
google/cloud/webrisk_v1beta1/services/__init__.py
google/cloud/webrisk_v1beta1/services/web_risk_service_v1_beta1/__init__.py
google/cloud/webrisk_v1beta1/services/web_risk_service_v1_beta1/async_client.py
google/cloud/webrisk_v1beta1/services/web_risk_service_v1_beta1/client.py
google/cloud/webrisk_v1beta1/services/web_risk_service_v1_beta1/transports/__init__.py
google/cloud/webrisk_v1beta1/services/web_risk_service_v1_beta1/transports/base.py
google/cloud/webrisk_v1beta1/services/web_risk_service_v1_beta1/transports/grpc.py
google/cloud/webrisk_v1beta1/services/web_risk_service_v1_beta1/transports/grpc_asyncio.py
google/cloud/webrisk_v1beta1/services/web_risk_service_v1_beta1/transports/rest.py
google/cloud/webrisk_v1beta1/services/web_risk_service_v1_beta1/transports/rest_base.py
google_cloud_webrisk-1.19.0.dist-info/licenses/LICENSE
google_cloud_webrisk-1.19.0.dist-info/METADATA
google_cloud_webrisk-1.19.0.dist-info/WHEEL
google_cloud_webrisk-1.19.0.dist-info/top_level.txt
google_cloud_webrisk-1.19.0.dist-info/RECORD
